gpsexif2csv/__init__.py
gpsexif2csv/main.py
gpsexif2csv-0.3.5.dist-info/entry_points.txt
gpsexif2csv-0.3.5.dist-info/LICENSE
gpsexif2csv-0.3.5.dist-info/METADATA
gpsexif2csv-0.3.5.dist-info/WHEEL
gpsexif2csv-0.3.5.dist-info/RECORD
